sentiscope.py
SENTISCOPE-0.2.1.dist-info/LICENSE.txt
SENTISCOPE-0.2.1.dist-info/METADATA
SENTISCOPE-0.2.1.dist-info/WHEEL
SENTISCOPE-0.2.1.dist-info/top_level.txt
SENTISCOPE-0.2.1.dist-info/RECORD
