Metadata-Version: 2.1
Name: SENTISCOPE
Version: 0.2.1
Summary: A package for financial news sentiment analysis and entity extraction
Home-page: https://github.com/kingsman1960/sentiscope
Author: Youngwon Cho
Author-email: youngwon.cho@tum.de
License: UNKNOWN
Platform: UNKNOWN
Classifier: Programming Language :: Python :: 3
Classifier: License :: OSI Approved :: MIT License
Classifier: Operating System :: OS Independent
License-File: LICENSE.txt
Requires-Dist: transformers
Requires-Dist: torch
Requires-Dist: nltk
Requires-Dist: flair
Requires-Dist: requests
